color_stream/__init__.py
color_stream/__main__.py
color_stream/core.py
color_stream-0.3.1.dist-info/METADATA
color_stream-0.3.1.dist-info/WHEEL
color_stream-0.3.1.dist-info/entry_points.txt
color_stream-0.3.1.dist-info/licenses/LICENSE
color_stream-0.3.1.dist-info/RECORD
