Metadata-Version: 2.4
Name: color_stream
Version: 0.3.1
Summary: A tool to run another shell command, and color the stdout/stderr streams green/red
Project-URL: homepage, https://github.com/DeflateAwning/color_stream
Project-URL: repository, https://github.com/DeflateAwning/color_stream
Project-URL: issues, https://github.com/DeflateAwning/color_stream/issues
Project-URL: pypi, https://pypi.org/project/color-stream/
Author: DeflateAwning
License-Expression: Unlicense
License-File: LICENSE
Classifier: License :: OSI Approved :: The Unlicense (Unlicense)
Classifier: Operating System :: OS Independent
Classifier: Programming Language :: Python :: 3
Provides-Extra: dev
Requires-Dist: pyright; extra == 'dev'
Requires-Dist: ruff; extra == 'dev'
